README.md
setup.py
ErrorFeed/__init__.py
errorfeed.egg-info/PKG-INFO
errorfeed.egg-info/SOURCES.txt
errorfeed.egg-info/dependency_links.txt
errorfeed.egg-info/top_level.txt