Metadata-Version: 2.1
Name: errorfeed
Version: 2.0.1
Summary: ErrorFeed client and WSGI middleware
Home-page: https://github.com/ErrorFeed/errorfeed-python
Author: Ken Kinder
Author-email: kkinder@errorfeed.com
License: Apache License (2.0)
Keywords: error feed errorfeed exception tracking api
Platform: UNKNOWN
Classifier: Programming Language :: Python
Classifier: Programming Language :: Python :: 2
Classifier: Programming Language :: Python :: 2.7
Classifier: Programming Language :: Python :: 3
Classifier: Programming Language :: Python :: 3.4
Classifier: Operating System :: OS Independent
Classifier: Programming Language :: Python
Classifier: Intended Audience :: Developers
